combocurve_api_v1/__init__.py
combocurve_api_v1/auth/__init__.py
combocurve_api_v1/auth/combocurve_auth.py
combocurve_api_v1/auth/jwt_handler.py
combocurve_api_v1/auth/service_account.py
combocurve_api_v1/auth/token_refresher.py
combocurve_api_v1/pagination/__init__.py
combocurve_api_v1/pagination/link.py
combocurve_api_v1-0.2.7.dist-info/METADATA
combocurve_api_v1-0.2.7.dist-info/WHEEL
combocurve_api_v1-0.2.7.dist-info/top_level.txt
combocurve_api_v1-0.2.7.dist-info/RECORD
