Metadata-Version: 2.1
Name: combocurve-api-v1
Version: 0.2.7
Summary: Client library for the ComboCurve REST API
Author: ComboCurve Inc
Classifier: Programming Language :: Python :: 3.9
Requires-Python: >=3.9.13
Requires-Dist: cffi==1.17.1
Requires-Dist: cryptography==43.0.3
Requires-Dist: pycparser==2.22
Requires-Dist: pyjwt[crypto]==2.9.0
